LICENSE
README.md
setup.cfg
setup.py
peoplenet_torch/__init__.py
peoplenet_torch/peoplenet.py
peoplenet_torch.egg-info/PKG-INFO
peoplenet_torch.egg-info/SOURCES.txt
peoplenet_torch.egg-info/dependency_links.txt
peoplenet_torch.egg-info/requires.txt
peoplenet_torch.egg-info/top_level.txt