Metadata-Version: 2.1
Name: peoplenet-torch
Version: 0.0.5
Summary: A Python package that allows you to run NVIDIA's PeopleNet using PyTorch
Home-page: https://github.com/paindefender/peoplenet_torch
Author: Kanat Alimanov
Author-email: 7l21@pm.me
Classifier: Programming Language :: Python :: 3
Classifier: Topic :: Software Development :: Libraries :: Python Modules
Classifier: Topic :: Scientific/Engineering :: Image Processing
Classifier: License :: OSI Approved :: GNU Affero General Public License v3 or later (AGPLv3+)
Classifier: Operating System :: OS Independent
Classifier: Development Status :: 3 - Alpha
Requires-Python: >=3.8
License-File: LICENSE
